soda_python_sdk/__init__.py
soda_python_sdk/crypto.py
soda_python_sdk/test.py
soda_sdk-0.0.1.dist-info/METADATA
soda_sdk-0.0.1.dist-info/WHEEL
soda_sdk-0.0.1.dist-info/top_level.txt
soda_sdk-0.0.1.dist-info/RECORD
