Metadata-Version: 2.1
Name: soda-sdk
Version: 0.0.1
Summary: This SDK provides functionalities for AES and RSA encryption schemes, ECDSA signature scheme and some functionalities used for working with sodalabs blockchain.
Home-page: https://github.com/soda-mpc/soda-sdk
Author: sodalabs
Author-email: meital@sodalabs.xyz
License: MIT
Classifier: Programming Language :: Python :: 3
Requires-Python: >=3.6
Requires-Dist: pycryptodome>=3.10.0
Requires-Dist: eth-keys>=0.3.3
Requires-Dist: cryptography>=3.4.7
Requires-Dist: web3==6.11.2
